setup.py
ln/__init__.py
ln/kb.py
ln/prueba.py
ln.egg-info/PKG-INFO
ln.egg-info/SOURCES.txt
ln.egg-info/dependency_links.txt
ln.egg-info/entry_points.txt
ln.egg-info/not-zip-safe
ln.egg-info/requires.txt
ln.egg-info/top_level.txt
ln/tests/__init__.py
ln/tests/alltests.py
ln/tests/doctests.py
ln/tests/testbase.py
