Metadata-Version: 1.0
Name: ln
Version: 0.1.3
Summary: natural language proof of concept
Home-page: http://pypi.python.org/pypi/nl
Author: Enrique Perez Arnaud
Author-email: enriquepablo@gmail.com
License: GPL
Keywords: natural language ai logic programming
Platform: UNKNOWN
